{
    "sourceFile": "resources/views/main/peminjaman_ruang/edit.blade.php",
    "activeCommit": 0,
    "commits": [
        {
            "activePatchIndex": 2,
            "patches": [
                {
                    "date": 1704834669046,
                    "content": "Index: \n===================================================================\n--- \n+++ \n"
                },
                {
                    "date": 1704835408389,
                    "content": "Index: \n===================================================================\n--- \n+++ \n@@ -25,13 +25,13 @@\n                     </div>\n                     <!-- /.card-header -->\n                     <div class=\"card-body\">\n \n-                        <form action=\"{{ route('peminjaman_mobil.update', $id) }}\" method=\"POST\" enctype=\"multipart/form-data\">\n+                        <form action=\"{{ route('peminjaman_ruang.update', $id) }}\" method=\"POST\" enctype=\"multipart/form-data\">\n                             @method('put')\n                             @csrf\n                             <div class=\"form-group\">\n-                                <label for=\"exampleFormControlTextarea1\">User ID</label>\n+                                <label for=\"exampleFormControlTextarea1\">Nama</label>\n                                 <select class=\"form-control\" name=\"user_id\">\n                                     @foreach ($user as $row)\n                                     <option value=\"{{ $row->id }}\">{{ $row->name }}</option>\n                                     @endforeach\n@@ -101,5 +101,5 @@\n         <!-- /.row -->\n     </div>\n     <!-- /.container-fluid -->\n </section>\n-@endsection\n\\ No newline at end of file\n+@endsection\n"
                },
                {
                    "date": 1704837809274,
                    "content": "Index: \n===================================================================\n--- \n+++ \n@@ -101,5 +101,38 @@\n         <!-- /.row -->\n     </div>\n     <!-- /.container-fluid -->\n </section>\n-@endsection\n\\ No newline at end of file\n+ <!-- Modal -->\n+ <div class=\"modal fade\" id=\"exampleModal\" tabindex=\"-1\" role=\"dialog\" aria-labelledby=\"exampleModalLabel\"\n+        aria-hidden=\"true\">\n+        <div class=\"modal-dialog\" role=\"document\">\n+            <div class=\"modal-content\">\n+                <form action=\"{{ route('peminjaman_ruang.print') }}\" method=\"POST\" enctype=\"multipart/form-data\">\n+                    @csrf\n+                    <div class=\"modal-header\">\n+                        <h5 class=\"modal-title\" id=\"exampleModalLabel\">Cetak Data</h5>\n+                        <button type=\"button\" class=\"close\" data-dismiss=\"modal\" aria-label=\"Close\">\n+                            <span aria-hidden=\"true\">&times;</span>\n+                        </button>\n+                    </div>\n+                    <div class=\"modal-body\">\n+\n+                        <div class=\"form-group\">\n+                            <label for=\"exampleFormControlTextarea1\">Tanggal Awal</label>\n+                            <input type=\"date\"class=\"form-control\" name=\"tgl_a\">\n+                        </div>\n+                        <div class=\"form-group\">\n+                            <label for=\"exampleFormControlTextarea1\">Tanggal Akhir</label>\n+                            <input type=\"date\"class=\"form-control\" name=\"tgl_b\">\n+                        </div>\n+                    </div>\n+                    <div class=\"modal-footer\">\n+                        <button type=\"button\" class=\"btn btn-secondary\" data-dismiss=\"modal\">Close</button>\n+                        <button type=\"submit\" class=\"btn btn-primary\">Cetak</button>\n+                    </div>\n+                </form>\n+            </div>\n+        </div>\n+    </div>\n+@endsection\n+\n"
                }
            ],
            "date": 1704834669046,
            "name": "Commit-0",
            "content": "@extends('layouts.layout_main')\n@section('content')\n    <section class=\"content\">\n        <div class=\"container-fluid\">\n            <div class=\"row\">\n                <div class=\"col-12\">\n                    <!-- /.card -->\n\n                    @if (session('success'))\n                        <div class=\"alert alert-success\">{{ session('success') }}</div>\n                    @endif\n\n                    @if (session('hapus'))\n                        <div class=\"alert alert-warning\">{{ session('hapus') }}</div>\n                    @endif\n                    @if ($errors->any())\n                        <div class=\"alert alert-danger\" role=\"alert\">\n                            {!! implode('', $errors->all('<li>:message</li>')) !!}\n                        </div>\n                    @endif\n\n                    <div class=\"card\">\n                        <div class=\"card-header\">\n                            <h3 class=\"card-title\">Form {{ $title }}</h3>\n                        </div>\n                        <!-- /.card-header -->\n                        <div class=\"card-body\">\n\n                            <form action=\"{{ route('peminjaman_mobil.update', $id) }}\" method=\"POST\"\n                                enctype=\"multipart/form-data\">\n                                @method('put')\n                                @csrf\n                                <div class=\"form-group\">\n                                    <label for=\"exampleFormControlTextarea1\">User ID</label>\n                                    <select class=\"form-control\" name=\"user_id\">\n                                        @foreach ($user as $row)\n                                            <option value=\"{{ $row->id }}\">{{ $row->name }}</option>\n                                        @endforeach\n                                    </select>\n                                </div>\n\n                                <div class=\"form-group\">\n                                    <label for=\"exampleFormControlTextarea1\">Ruangan</label>\n                                    <select class=\"form-control\" name=\"mobil_id\">\n                                        @foreach ($ruang as $row)\n                                            <option value=\"{{ $row->id }}\">{{ $row->nama }}</option>\n                                        @endforeach\n                                    </select>\n                                </div>\n\n                                <div class=\"form-group\">\n                                    <label for=\"exampleFormControlTextarea1\">Kegiatan</label>\n                                    <input type=\"text\"class=\"form-control\" name=\"kegiatan\" value=\"{{ $kegiatan }}\">\n                                </div>\n                                <div class=\"form-group\">\n                                    <label for=\"exampleFormControlTextarea1\">Jam Mulai</label>\n                                    <input type=\"text\"class=\"form-control\" name=\"mulai\" value=\"{{ $mulai }}\">\n                                </div>\n\n                                <div class=\"form-group\">\n                                    <label for=\"exampleFormControlTextarea1\">Selesai</label>\n                                    <input type=\"text\"class=\"form-control\" name=\"selesai\"\n                                        value=\"{{ $selesai }}\">\n                                </div>\n\n                                <div class=\"form-group\">\n                                    <label for=\"exampleFormControlTextarea1\">Tanggal</label>\n                                    <input type=\"date\"class=\"form-control\" name=\"tanggal\"\n                                        value=\"{{ $tanggal }}\">\n                                </div>\n\n\n                                @if (auth()->user()->jab_id == 1 || auth()->user()->jab_id == 2 || auth()->user()->jab_id == 3)\n                                    <div class=\"form-group\">\n                                        <label for=\"exampleFormControlTextarea1\">Status</label>\n                                        <select class=\"form-control\" name=\"status\">\n\n                                            <option value=\"{{ $status }}\" selected>{{ $status }}</option>\n                                            <option value=\"pending\">pending</option>\n                                            <option value=\"approved\">approved</option>\n                                            <option value=\"rejected\">rejected</option>\n                                        </select>\n                                    </div>\n                                @endif\n\n\n                                @if (auth()->user()->jab_id == 4)\n                                    <div class=\"form-group\">\n                                        <label for=\"exampleFormControlTextarea1\">Status</label>\n                                        <select class=\"form-control\" name=\"status\">\n                                            <option value=\"{{ $status }}\" selected>{{ $status }}</option>\n                                        </select>\n                                    </div>\n                                @endif\n                                <button type=\"submit\" class=\"btn btn-primary\">Simpan</button>\n                            </form>\n                        </div>\n                        <!-- /.card-body -->\n                    </div>\n                    <!-- /.card -->\n                </div>\n                <!-- /.col -->\n            </div>\n            <!-- /.row -->\n        </div>\n        <!-- /.container-fluid -->\n    </section>\n@endsection\n"
        }
    ]
}